<?xml version="1.0" encoding="UTF-8"?>
<BuildStatus>
    <Strategy name="Strategy1">
        <Milestone name="Export" build_result="0" build_time="0">
            <Task name="IBIS" build_result="0" update_result="3" update_time="0"/>
            <Task name="TimingSimFileVlg" build_result="0" update_result="3" update_time="0"/>
            <Task name="TimingSimFileVHD" build_result="0" update_result="3" update_time="0"/>
            <Task name="Bitgen" build_result="0" update_result="3" update_time="0"/>
            <Task name="Jedecgen" build_result="2" update_result="0" update_time="1557274940"/>
        </Milestone>
        <Milestone name="Map" build_result="2" build_time="1557274915">
            <Task name="Map" build_result="2" update_result="0" update_time="1557274915"/>
            <Task name="MapTrace" build_result="0" update_result="3" update_time="0"/>
            <Task name="MapVerilogSimFile" build_result="0" update_result="3" update_time="0"/>
            <Task name="MapVHDLSimFile" build_result="0" update_result="3" update_time="0"/>
        </Milestone>
        <Milestone name="PAR" build_result="2" build_time="1557274934">
            <Task name="PAR" build_result="2" update_result="0" update_time="1557274934"/>
            <Task name="PARTrace" build_result="0" update_result="3" update_time="0"/>
            <Task name="IOTiming" build_result="0" update_result="3" update_time="0"/>
        </Milestone>
        <Milestone name="Synthesis" build_result="2" build_time="1557273712">
            <Task name="Synplify_Synthesis" build_result="2" update_result="0" update_time="1557273712"/>
        </Milestone>
        <Milestone name="TOOL_Report" build_result="0" build_time="0">
            <Task name="HDLE" build_result="2" update_result="0" update_time="1557327609"/>
            <Task name="BKM" build_result="0" update_result="2" update_time="0"/>
            <Task name="SSO" build_result="0" update_result="2" update_time="0"/>
            <Task name="PIODRC" build_result="0" update_result="2" update_time="0"/>
            <Task name="DEC" build_result="0" update_result="2" update_time="0"/>
        </Milestone>
        <Milestone name="Translate" build_result="2" build_time="1557273714">
            <Task name="Translate" build_result="2" update_result="0" update_time="1557273714"/>
        </Milestone>
        <Report name="alu01_alu01.bgn" last_build_time="1557274940" last_build_size="4225"/>
        <Report name="alu01_alu01.edi" last_build_time="1557273710" last_build_size="786064"/>
        <Report name="alu01_alu01.jed" last_build_time="1557274940" last_build_size="1465927"/>
        <Report name="alu01_alu01.ncd" last_build_time="1557274934" last_build_size="476900"/>
        <Report name="alu01_alu01.ngd" last_build_time="1557273714" last_build_size="502327"/>
        <Report name="alu01_alu01_map.ncd" last_build_time="1557274915" last_build_size="322518"/>
    </Strategy>
</BuildStatus>
